koksl_to_elan/__init__.py
koksl_to_elan/cli.py
koksl_to_elan/convert.py
koksl_to_elan/generate.py
koksl_to_elan-0.1.8.dist-info/entry_points.txt
koksl_to_elan-0.1.8.dist-info/METADATA
koksl_to_elan-0.1.8.dist-info/WHEEL
koksl_to_elan-0.1.8.dist-info/RECORD
