Metadata-Version: 2.1
Name: koksl-to-elan
Version: 0.1.8
Summary: 국립국어원 한국어-한국수어 병렬 말뭉치를 ELAN 형식(eaf)으로 변환하는 도구
Author: Yeonwoo Kim
Author-email: wiskingdom@gmail.com
Requires-Python: >=3.11,<4.0
Classifier: Programming Language :: Python :: 3
Classifier: Programming Language :: Python :: 3.11
Classifier: Programming Language :: Python :: 3.12
